{
  "lastUpdated": "2025-05-26T00:26:10.210Z",
  "directories": {
    "2025.04.15": [
      {
        "name": "2025.04.15.A.md",
        "path": "content/2025.04.15/2025.04.15.A.md"
      },
      {
        "name": "2025.04.15.B.md",
        "path": "content/2025.04.15/2025.04.15.B.md"
      },
      {
        "name": "2025.04.15.C.md",
        "path": "content/2025.04.15/2025.04.15.C.md"
      },
      {
        "name": "2025.04.15.D.md",
        "path": "content/2025.04.15/2025.04.15.D.md"
      }
    ],
    "Hamlet": [
      {
        "name": "Act I.md",
        "path": "content/Hamlet/Act I.md"
      }
    ]
  }
}